tronpynet/__init__.py
tronpynet/main.py
tronpynet-0.0.1.dist-info/LICENSE.txt
tronpynet-0.0.1.dist-info/METADATA
tronpynet-0.0.1.dist-info/WHEEL
tronpynet-0.0.1.dist-info/top_level.txt
tronpynet-0.0.1.dist-info/RECORD
