Metadata-Version: 2.1
Name: tronpynet
Version: 0.0.1
Summary: tronpynet library for Python
Author: dimatron
Author-email: sanimw2402@gmail.com
License: MIT
Project-URL: Source Repository, https://github.com/dcnstrn/tronwebpy
License-File: LICENSE.txt
Requires-Dist: requests
